mimic_useragent/__init__.py
mimic_useragent-0.1.3.dist-info/LICENSE
mimic_useragent-0.1.3.dist-info/METADATA
mimic_useragent-0.1.3.dist-info/WHEEL
mimic_useragent-0.1.3.dist-info/RECORD
