Metadata-Version: 2.1
Name: mimic-useragent
Version: 0.1.3
Summary: Simple user-agent generator (Firefox).
Home-page: https://github.com/kurotom/mimic_useragent
License: LGPL-3.0-or-later
Author: kurotom
Author-email: 55354389+kurotom@users.noreply.github.com
Requires-Python: >=3.7,<4.0
Classifier: License :: OSI Approved :: GNU Lesser General Public License v3 or later (LGPLv3+)
Classifier: Programming Language :: Python :: 3
Classifier: Programming Language :: Python :: 3.7
Classifier: Programming Language :: Python :: 3.8
Classifier: Programming Language :: Python :: 3.9
Classifier: Programming Language :: Python :: 3.10
Classifier: Programming Language :: Python :: 3.11
Classifier: Topic :: Internet :: WWW/HTTP
Project-URL: Bug Tracker, https://github.com/kurotom/mimic_useragent/issues
Project-URL: Repository, https://github.com/kurotom/mimic_useragent
